{
    "Ar36": {
        "error": 0.00013158644642270758,
        "error_type": "",
        "fit": "Weighted Mean_SD",
        "references": [
            {
                "exclude": "omit",
                "record_id": "ba-03-F-86",
                "uuid": "68b72ff8-c9e1-4e38-a5fe-6716a90a15bf"
            },
            {
                "exclude": "ok",
                "record_id": "ba-03-F-87",
                "uuid": "3dfc9db1-9fb1-43aa-b247-8b1cb09b5bb1"
            },
            {
                "exclude": "ok",
                "record_id": "ba-03-F-88",
                "uuid": "1e13c415-f541-4bec-b213-fabf259dc481"
            },
            {
                "exclude": "ok",
                "record_id": "ba-03-F-89",
                "uuid": "a23d8cd1-dc02-49b9-b3a3-08765590ed75"
            },
            {
                "exclude": "omit",
                "record_id": "ba-03-F-90",
                "uuid": "6d6348a8-461e-48dd-ab78-416bc88e7fef"
            },
            {
                "exclude": "omit",
                "record_id": "ba-03-F-91",
                "uuid": "a85c8843-c2d5-4ade-bb85-d9e10a540c9a"
            }
        ],
        "reviewed": true,
        "value": 0.001829625991756673
    },
    "Ar37": {
        "error": 0.02043961145093529,
        "error_type": "",
        "fit": "Weighted Mean_SD",
        "references": [
            {
                "exclude": "omit",
                "record_id": "ba-03-F-86",
                "uuid": "68b72ff8-c9e1-4e38-a5fe-6716a90a15bf"
            },
            {
                "exclude": "ok",
                "record_id": "ba-03-F-87",
                "uuid": "3dfc9db1-9fb1-43aa-b247-8b1cb09b5bb1"
            },
            {
                "exclude": "ok",
                "record_id": "ba-03-F-88",
                "uuid": "1e13c415-f541-4bec-b213-fabf259dc481"
            },
            {
                "exclude": "ok",
                "record_id": "ba-03-F-89",
                "uuid": "a23d8cd1-dc02-49b9-b3a3-08765590ed75"
            },
            {
                "exclude": "omit",
                "record_id": "ba-03-F-90",
                "uuid": "6d6348a8-461e-48dd-ab78-416bc88e7fef"
            },
            {
                "exclude": "omit",
                "record_id": "ba-03-F-91",
                "uuid": "a85c8843-c2d5-4ade-bb85-d9e10a540c9a"
            }
        ],
        "reviewed": true,
        "value": 0.002022883758882151
    },
    "Ar38": {
        "error": 0.002928365261824955,
        "error_type": "",
        "fit": "Weighted Mean_SD",
        "references": [
            {
                "exclude": "omit",
                "record_id": "ba-03-F-86",
                "uuid": "68b72ff8-c9e1-4e38-a5fe-6716a90a15bf"
            },
            {
                "exclude": "ok",
                "record_id": "ba-03-F-87",
                "uuid": "3dfc9db1-9fb1-43aa-b247-8b1cb09b5bb1"
            },
            {
                "exclude": "ok",
                "record_id": "ba-03-F-88",
                "uuid": "1e13c415-f541-4bec-b213-fabf259dc481"
            },
            {
                "exclude": "ok",
                "record_id": "ba-03-F-89",
                "uuid": "a23d8cd1-dc02-49b9-b3a3-08765590ed75"
            },
            {
                "exclude": "omit",
                "record_id": "ba-03-F-90",
                "uuid": "6d6348a8-461e-48dd-ab78-416bc88e7fef"
            },
            {
                "exclude": "omit",
                "record_id": "ba-03-F-91",
                "uuid": "a85c8843-c2d5-4ade-bb85-d9e10a540c9a"
            }
        ],
        "reviewed": true,
        "value": 0.0054645950124564335
    },
    "Ar39": {
        "error": 0.01308253279139585,
        "error_type": "",
        "fit": "Weighted Mean_SD",
        "references": [
            {
                "exclude": "omit",
                "record_id": "ba-03-F-86",
                "uuid": "68b72ff8-c9e1-4e38-a5fe-6716a90a15bf"
            },
            {
                "exclude": "ok",
                "record_id": "ba-03-F-87",
                "uuid": "3dfc9db1-9fb1-43aa-b247-8b1cb09b5bb1"
            },
            {
                "exclude": "ok",
                "record_id": "ba-03-F-88",
                "uuid": "1e13c415-f541-4bec-b213-fabf259dc481"
            },
            {
                "exclude": "ok",
                "record_id": "ba-03-F-89",
                "uuid": "a23d8cd1-dc02-49b9-b3a3-08765590ed75"
            },
            {
                "exclude": "omit",
                "record_id": "ba-03-F-90",
                "uuid": "6d6348a8-461e-48dd-ab78-416bc88e7fef"
            },
            {
                "exclude": "omit",
                "record_id": "ba-03-F-91",
                "uuid": "a85c8843-c2d5-4ade-bb85-d9e10a540c9a"
            }
        ],
        "reviewed": true,
        "value": 0.03538518140551656
    },
    "Ar40": {
        "error": 0.060526230360029,
        "error_type": "",
        "fit": "Weighted Mean_SD",
        "references": [
            {
                "exclude": "omit",
                "record_id": "ba-03-F-86",
                "uuid": "68b72ff8-c9e1-4e38-a5fe-6716a90a15bf"
            },
            {
                "exclude": "ok",
                "record_id": "ba-03-F-87",
                "uuid": "3dfc9db1-9fb1-43aa-b247-8b1cb09b5bb1"
            },
            {
                "exclude": "ok",
                "record_id": "ba-03-F-88",
                "uuid": "1e13c415-f541-4bec-b213-fabf259dc481"
            },
            {
                "exclude": "ok",
                "record_id": "ba-03-F-89",
                "uuid": "a23d8cd1-dc02-49b9-b3a3-08765590ed75"
            },
            {
                "exclude": "omit",
                "record_id": "ba-03-F-90",
                "uuid": "6d6348a8-461e-48dd-ab78-416bc88e7fef"
            },
            {
                "exclude": "omit",
                "record_id": "ba-03-F-91",
                "uuid": "a85c8843-c2d5-4ade-bb85-d9e10a540c9a"
            }
        ],
        "reviewed": true,
        "value": 0.16262210360442209
    }
}